{"cameraMode":{"drawMode":0,"name":"Shaded","section":"Shading Mode"},"sceneLighting":true,"audioPlay":false,"sceneViewState":{"showFog":true,"showMaterialUpdate":false,"showSkybox":true,"showFlares":true,"showImageEffects":true,"showParticleSystems":true},"in2DMode":false,"pivot":{"x":47.97618103027344,"y":-18.90780258178711,"z":18.92184829711914},"rotation":{"x":0.12093286961317063,"y":0.6072943806648254,"z":-0.09420160949230194,"w":0.7795640826225281},"size":34.87238311767578,"orthographic":false}